{"textures":{"0":"modelengine:entity/sculk_sentinel"},"elements":[{"from":[4.475,-6.025,3.975],"to":[11.525,8.025,12.025],"faces":{"east":{"uv":[7.625,3.5,8.625,5.25],"tintindex":0,"rotation":0,"texture":"#0"},"south":{"uv":[9.125,0.0,10.0,1.75],"tintindex":0,"rotation":0,"texture":"#0"},"north":{"uv":[8.875,7.875,9.75,9.625],"tintindex":0,"rotation":0,"texture":"#0"},"west":{"uv":[7.625,5.25,8.625,7.0],"tintindex":0,"rotation":0,"texture":"#0"},"up":{"uv":[6.25,13.0,5.375,12.0],"tintindex":0,"rotation":0,"texture":"#0"},"down":{"uv":[7.125,12.0,6.25,13.0],"tintindex":0,"rotation":0,"texture":"#0"}}}],"display":{"gui":{"rotation":[30,225,0]}}}