{"textures":{"0":"modelengine:entity/bl_shadow_spider"},"elements":[{"from":[7.0956697,6.75607,5.2623796],"to":[9.09567,8.75607,9.26238],"faces":{"east":{"uv":[10.75,5.25,11.75,5.75],"tintindex":0,"rotation":0,"texture":"#0"},"south":{"uv":[11.75,0.0,12.25,0.5],"tintindex":0,"rotation":0,"texture":"#0"},"north":{"uv":[11.5,3.75,12.0,4.25],"tintindex":0,"rotation":0,"texture":"#0"},"west":{"uv":[10.75,5.75,11.75,6.25],"tintindex":0,"rotation":0,"texture":"#0"},"up":{"uv":[11.25,7.25,10.75,6.25],"tintindex":0,"rotation":0,"texture":"#0"},"down":{"uv":[7.75,10.75,7.25,11.75],"tintindex":0,"rotation":0,"texture":"#0"}}}],"display":{"gui":{"rotation":[30,225,0]}}}